MANIFEST.in
setup.py
crickit/PlayCricket.py
crickit/__init__.py
crickit/simulate.py
crickit/teams.py
crickit/teamsList.py
crickit.egg-info/PKG-INFO
crickit.egg-info/SOURCES.txt
crickit.egg-info/dependency_links.txt
crickit.egg-info/top_level.txt
docs/README.rst