Metadata-Version: 1.0
Name: crickit
Version: 0.0.125
Summary: Text based Cricket Simulator in Python
Home-page: https://github.com/oficiallyAkshayEdu/crickit
Author: Akshay Agrawal
Author-email: UNKNOWN
License: MITa
Platform: UNKNOWN
